sml_test/__init__.py
sml_test/cli.py
sml_test/main.py
sml_test-1.3.0.dist-info/LICENSE.md
sml_test-1.3.0.dist-info/METADATA
sml_test-1.3.0.dist-info/WHEEL
sml_test-1.3.0.dist-info/entry_points.txt
sml_test-1.3.0.dist-info/top_level.txt
sml_test-1.3.0.dist-info/RECORD
