Metadata-Version: 2.1
Name: sml-test
Version: 1.3.0
Summary: The CLI tool to recursively run all SML tests in a directory
Home-page: https://github.com/lancelote/sml-test
Author: Pavel Karateev
Author-email: lancelote.du.lac@gmail.com
License: MIT
Platform: UNKNOWN
Classifier: License :: OSI Approved :: MIT License
Classifier: Programming Language :: Python :: 3
Classifier: Programming Language :: Python :: 3 :: Only
Classifier: Programming Language :: Python :: 3.8
Classifier: Programming Language :: Python :: 3.9
Classifier: Programming Language :: Python :: Implementation :: CPython
Requires-Python: >=3.8
License-File: LICENSE.md
Requires-Dist: click
Requires-Dist: importlib-metadata ; python_version < "3.8"
